version_get/__init__.py
version_get/version_get.py
version_get-1.0.13.dist-info/licenses/LICENSE
version_get-1.0.13.dist-info/METADATA
version_get-1.0.13.dist-info/WHEEL
version_get-1.0.13.dist-info/entry_points.txt
version_get-1.0.13.dist-info/top_level.txt
version_get-1.0.13.dist-info/RECORD
