Metadata-Version: 2.4
Name: version_get
Version: 1.0.13
Summary: A robust version management utility for Python projects
Home-page: https://github.com/cumulus13/version_get
Author: cumulus13
Author-email: cumulus13@gmail.com
License-Expression: MIT
Project-URL: Homepage, https://github.com/cumulus13/version_get
Project-URL: Bug Reports, https://github.com/cumulus13/version_get/issues
Project-URL: Source, https://github.com/cumulus13/version_get
Keywords: version,versioning,semver,semantic-versioning,version-management
Classifier: Development Status :: 5 - Production/Stable
Classifier: Intended Audience :: Developers
Classifier: Programming Language :: Python :: 3
Classifier: Programming Language :: Python :: 3.6
Classifier: Programming Language :: Python :: 3.7
Classifier: Programming Language :: Python :: 3.8
Classifier: Programming Language :: Python :: 3.9
Classifier: Programming Language :: Python :: 3.10
Classifier: Programming Language :: Python :: 3.11
Classifier: Programming Language :: Python :: 3.12
Classifier: Topic :: Software Development :: Libraries :: Python Modules
Classifier: Topic :: Software Development :: Version Control
Classifier: Topic :: Utilities
Requires-Python: >=3.6
License-File: LICENSE
Provides-Extra: dev
Requires-Dist: pytest>=6.0; extra == "dev"
Requires-Dist: pytest-cov>=2.0; extra == "dev"
Requires-Dist: black>=21.0; extra == "dev"
Requires-Dist: flake8>=3.9; extra == "dev"
Requires-Dist: mypy>=0.900; extra == "dev"
Dynamic: author-email
Dynamic: home-page
Dynamic: license-file
Dynamic: requires-python
